exasol_error_reporting_python/__init__.py
exasol_error_reporting_python/error_message_builder.py
exasol_error_reporting_python/exa_error.py
exasol_error_reporting_python/parameters_mapper.py
exasol_error_reporting_python/placeholder.py
exasol_error_reporting_python/placeholder_handler.py
exasol_error_reporting_python-0.3.0.dist-info/LICENSE
exasol_error_reporting_python-0.3.0.dist-info/WHEEL
exasol_error_reporting_python-0.3.0.dist-info/METADATA
exasol_error_reporting_python-0.3.0.dist-info/RECORD
