Metadata-Version: 2.1
Name: exasol-error-reporting-python
Version: 0.3.0
Summary: Exasol Python Error Reporting
Home-page: https://github.com/exasol/error-reporting-python
License: MIT
Keywords: exasol,python,error-reporting
Author: Umit Buyuksahin
Author-email: umit.buyuksahin@exasol.com
Requires-Python: >=3.8,<4.0
Classifier: License :: OSI Approved :: MIT License
Classifier: Programming Language :: Python :: 3
Classifier: Programming Language :: Python :: 3.8
Classifier: Programming Language :: Python :: 3.9
Classifier: Programming Language :: Python :: 3.10
Project-URL: Repository, https://github.com/exasol/error-reporting-python
